comfo/__init__.py
comfo/client.py
comfo/comfo_pb2.py
comfo/comfo_twirp.py
comfo/exceptions.py
comfo/types.py
comfo-0.3.0.dist-info/METADATA
comfo-0.3.0.dist-info/WHEEL
comfo-0.3.0.dist-info/top_level.txt
comfo-0.3.0.dist-info/RECORD
