Metadata-Version: 2.1
Name: comfo
Version: 0.3.0
Summary: Python API client for comfo, a Zehnder ComfoAir home         automation controller.
Home-page: https://github.com/ti-mo/comfo
Author: Timo Beckers
Author-email: timo@incline.eu
License: MIT
Requires-Python: >=3.6
Requires-Dist: twirp (==0.0.3)
